pyImageJGui/__init__.py
pyImageJGui/icon/icon.py
pyImageJGui/style/main.qss
pyImageJGui/style/qssloader.py
pyImageJGui/ui/AngleRoi.py
pyImageJGui/ui/CircleRoi.py
pyImageJGui/ui/CircleRoi1.py
pyImageJGui/ui/EllipseRoi.py
pyImageJGui/ui/LineRoi.py
pyImageJGui/ui/PointRoi.py
pyImageJGui/ui/RectangleRoi.py
pyImageJGui/ui/constant.py
pyImageJGui/ui/gui.py
pyImageJGui/ui/imageView.py
pyImageJGui/ui/plot.py
pyImageJGui/utils/function.py
pyimagejgui-0.0.26.dist-info/METADATA
pyimagejgui-0.0.26.dist-info/WHEEL
pyimagejgui-0.0.26.dist-info/licenses/LICENSE
pyimagejgui-0.0.26.dist-info/RECORD
